odoo/addons/to_many_tracking/__init__.py
odoo/addons/to_many_tracking/__manifest__.py
odoo/addons/to_many_tracking/models/__init__.py
odoo/addons/to_many_tracking/models/mail_tracking_value.py
odoo_to_many_tracking-14.0.0.dist-info/LICENSE
odoo_to_many_tracking-14.0.0.dist-info/METADATA
odoo_to_many_tracking-14.0.0.dist-info/WHEEL
odoo_to_many_tracking-14.0.0.dist-info/top_level.txt
odoo_to_many_tracking-14.0.0.dist-info/RECORD
