Metadata-Version: 2.1
Name: odoo-to-many-tracking
Version: 14.0.0
Summary: To-many tracking module for Odoo
Home-page: https://github.com/andersinno/odoo-to-many-tracking
Author: Anders Innovations
Author-email: support@anders.fi
License: UNKNOWN
Platform: UNKNOWN
